{"noMoreComments": true, "cursorEnd": 0, "id": "7719503", "comments": [{"postBy": {"location": "", "utc": 1518714613000, "level": 0, "avatar": "http://filestoresg1.beetalkmobile.com:8081/file/-316868232744753404", "name": "\u5f35\u7c73\u5947"}, "content": "\u55e8\u55e8", "urls": [], "replies": {"first": [], "last": [], "noMoreReplies": true}, "images": [], "id": 81817447}, {"postBy": {"location": "", "utc": 1518726682000, "level": 0, "avatar": "http://filestoresg1.beetalkmobile.com:8081/file/-3888434962023645695", "name": "TOP"}, "content": "\u6211\u4f86\u611b\u4e86", "urls": [], "replies": {"first": [], "last": [], "noMoreReplies": true}, "images": [], "id": 81824354}, {"postBy": {"location": "\u9ad8\u96c4\u5e02\u00b7\u53f0\u7063", "utc": 1518808450000, "level": 0, "avatar": "http://filestoresg1.beetalkmobile.com:8081/file/-5859249082082092430", "name": "\u9673"}, "content": "\u6240\u4ee5\u6211\u624d\u9084\u6d3b\u8457", "urls": [], "replies": {"first": [], "last": [], "noMoreReplies": true}, "images": [], "id": 81885675}, {"postBy": {"location": "\u9ad8\u96c4\u5e02\u00b7\u53f0\u7063", "utc": 1518931632000, "level": 0, "avatar": "http://filestoresg1.beetalkmobile.com:8081/file/-3944227460458024559", "name": "\u5446\u5446\u5bb6\u5b8f"}, "content": "\u611b\u59b3\u4e0d\u6703\u6b7b", "urls": [], "replies": {"first": [], "last": [], "noMoreReplies": true}, "images": [], "id": 81976775}, {"postBy": {"location": "\u9ad8\u96c4\u5e02\u00b7\u53f0\u7063", "utc": 1519043693000, "level": 0, "avatar": "http://filestoresg1.beetalkmobile.com:8081/file/-5139945256226353054", "name": "\u8def\u6613"}, "content": "\u8981\u5e7e\u4e0b\u90fd\u7d66\u59b3\uff0c\u54c8", "urls": [], "replies": {"first": [], "last": [], "noMoreReplies": true}, "images": [], "id": 82067996}, {"postBy": {"location": "\u53f0\u7063", "utc": 1519100326000, "level": 0, "avatar": "http://filestoresg1.beetalkmobile.com:8081/file/-3200072495968065470", "name": "\u7f8e\u5473\u87f9\u5821\ud83d\ude06\ud83d\ude06"}, "content": "\u4e0d\u6703\u554a", "urls": [], "replies": {"first": [], "last": [], "noMoreReplies": true}, "images": [], "id": 82112579}, {"postBy": {"location": "\u53f0\u7063", "utc": 1519842185000, "level": 0, "avatar": "http://filestoresg1.beetalkmobile.com:8081/file/-5980501007203918997", "name": "*****"}, "content": "\u9738\u6c23", "urls": [], "replies": {"first": [], "last": [], "noMoreReplies": true}, "images": [], "id": 82717960}, {"postBy": {"location": "\u53f0\u7063", "utc": 1520012316000, "level": 0, "avatar": "http://filestoresg1.beetalkmobile.com:8081/file/-5175589226079987521", "name": "\u9673\u4fe1"}, "content": "\u8f9b\u82e6\u4e86", "urls": [], "replies": {"first": [], "last": [], "noMoreReplies": true}, "images": [], "id": 82847775}, {"postBy": {"location": "", "utc": 1520165189000, "level": 0, "avatar": "http://filestoresg1.beetalkmobile.com:8081/file/2555671854073913194", "name": "\u5976\u5634"}, "content": "\u7d66\u611b\u55ce\uff1f", "urls": [], "replies": {"first": [], "last": [], "noMoreReplies": true}, "images": [], "id": 82962369}, {"postBy": {"location": "", "utc": 1520225742000, "level": 0, "avatar": "http://filestoresg1.beetalkmobile.com:8081/file/7400862245911399936", "name": "\u51e1\u8d70\u904e\u5fc5\u7559\u4e0b\u75d5\u8de1"}, "content": "\u82d7\u6817\u4eba\u4e00\u8d77\u8a8d\u8b58\u4e00\u4e0b", "urls": [], "replies": {"first": [], "last": [], "noMoreReplies": true}, "images": [], "id": 83008187}, {"postBy": {"location": "\u65b0\u5317\u5e02\u00b7\u53f0\u7063", "utc": 1520302099000, "level": 0, "avatar": "http://filestoresg1.beetalkmobile.com:8081/file/4315155433710714031", "name": "."}, "content": "\u6211\u611b\u59b3~", "urls": [], "replies": {"first": [], "last": [], "noMoreReplies": true}, "images": [], "id": 83070736}, {"postBy": {"location": "\u53f0\u7063", "utc": 1520492242000, "level": 0, "avatar": "http://filestoresg1.beetalkmobile.com:8081/file/5913284608644829204", "name": "\u9ed8\u5440"}, "content": "\u6703\u6b7b\uff01<br />\u56e0\u70ba\u4e00\u4e0b\u4e0d\u5920\uff01", "urls": [], "replies": {"first": [], "last": [], "noMoreReplies": true}, "images": [], "id": 83227173}, {"postBy": {"location": "\u53f0\u7063", "utc": 1526619763000, "level": 0, "avatar": "http://filestoresg1.beetalkmobile.com:8081/file/4880305530074877657", "name": "\u83ab\u9808\u554f"}, "content": "\u6211\u53ef\u4ee5\u55ce", "urls": [], "replies": {"first": [], "last": [], "noMoreReplies": true}, "images": [], "id": 88368373}]}
