{"noMoreComments": false, "cursorEnd": 21, "id": "7163187", "comments": [{"postBy": {"location": "", "utc": 1512328616000, "level": 0, "avatar": "http://filestoresg1.beetalkmobile.com:8081/file/-4923250229349290366", "name": "Eason"}, "content": "\u6709\u6bd4\u6211\u5f85\u5728\u99ac\u7956\u7576\u5175\u9867\u6c34\u5ee0\u7121\u804a\u55ce\uff1f", "urls": [], "replies": {"first": [{"content": "\u8f9b\u82e6\u4e86", "reply": "", "id": 52280299, "name": "\u5c4f\u6771\u4eba"}], "last": [], "noMoreReplies": true}, "images": [], "id": 77033529}, {"postBy": {"location": "\u6843\u5712\u5e02\u00b7\u53f0\u7063", "utc": 1512988676000, "level": 0, "avatar": "http://filestoresg1.beetalkmobile.com:8081/file/5459693158586423356", "name": "\u60f3\u627e\u500b\u4eba\u7a69\u5b9a\u6216\u7a69\u804a\u771f\u96e3"}, "content": "\u6c92\u5ba2\u4eba\u7684\u6642\u9593\u771f\u7684\u5f88\u7121\u804a", "urls": [], "replies": {"first": [{"content": "\u54ea\u7a2e\u610f\u601d...\uff1f", "reply": "", "id": 52280306, "name": "\u5c4f\u6771\u4eba"}], "last": [], "noMoreReplies": true}, "images": [], "id": 77515685}, {"postBy": {"location": "\u65b0\u5317\u5e02\u00b7\u53f0\u7063", "utc": 1513170042000, "level": 0, "avatar": "http://filestoresg1.beetalkmobile.com:8081/file/-71685935567510998", "name": "\u58a8\u7fbd"}, "content": "\u59b3\u7684\u8ffd\u8e64\u8005\u8d85\u591a\u2026\u2026\u2026", "urls": [], "replies": {"first": [], "last": [], "noMoreReplies": true}, "images": [], "id": 77649126}, {"postBy": {"location": "", "utc": 1513174199000, "level": 0, "avatar": "http://filestoresg1.beetalkmobile.com:8081/file/1650317476475140939", "name": "\u4f86\u804a\u5929"}, "content": "\u7121\u804a\u5230\u767c\u8352", "urls": [], "replies": {"first": [], "last": [], "noMoreReplies": true}, "images": [], "id": 77653836}, {"postBy": {"location": "", "utc": 1513213851000, "level": 0, "avatar": "http://filestoresg1.beetalkmobile.com:8081/file/1", "name": "\u5c0f\u6587"}, "content": "\u5b89\u5b89", "urls": [], "replies": {"first": [], "last": [], "noMoreReplies": true}, "images": [], "id": 77678591}, {"postBy": {"location": "\u6843\u5712\u5e02\u00b7\u53f0\u7063", "utc": 1513233132000, "level": 0, "avatar": "http://filestoresg1.beetalkmobile.com:8081/file/6816016617485363500", "name": "\u9716"}, "content": "\u597d\u5594\u8df3\u9336\u8a08\u8cbb\u54e6", "urls": [], "replies": {"first": [], "last": [], "noMoreReplies": true}, "images": [], "id": 77692397}, {"postBy": {"location": "\u65b0\u5317\u5e02\u00b7\u53f0\u7063", "utc": 1513240744000, "level": 0, "avatar": "http://filestoresg1.beetalkmobile.com:8081/file/-1268828701793302783", "name": "Kevin"}, "content": "\u804a\u4ec0\u9ebc\ud83e\udd28\ud83e\udd28", "urls": [], "replies": {"first": [], "last": [], "noMoreReplies": true}, "images": [], "id": 77697660}, {"postBy": {"location": "", "utc": 1513470389000, "level": 0, "avatar": "http://filestoresg1.beetalkmobile.com:8081/file/1850483582735226135", "name": "Unique"}, "content": "\u5982\u679c\u771f\u7684\u7121\u804a\uff1a\u600e\u9ebc\u6c92\u53bb\u627e\u7a3b\u8349\u4eba\u966a\u59b3\u5462\uff1f=.=", "urls": [], "replies": {"first": [], "last": [], "noMoreReplies": true}, "images": [], "id": 77859258}, {"postBy": {"location": "\u53f0\u4e2d\u5e02\u00b7\u53f0\u7063", "utc": 1513592950000, "level": 0, "avatar": "http://filestoresg1.beetalkmobile.com:8081/file/2117930998435902764", "name": "\u5b54\u660e"}, "content": "\u6b63\u59b9", "urls": [], "replies": {"first": [], "last": [], "noMoreReplies": true}, "images": [], "id": 77946346}, {"postBy": {"location": "\u9ad8\u96c4\u5e02\u00b7\u53f0\u7063", "utc": 1513602659000, "level": 0, "avatar": "http://filestoresg1.beetalkmobile.com:8081/file/-9188566994640446890", "name": "\u661f\u661fIG\ud83d\udc49silentorz"}, "content": "\u54c8\u56c9", "urls": [], "replies": {"first": [], "last": [], "noMoreReplies": true}, "images": [], "id": 77955031}, {"postBy": {"location": "\u9ad8\u96c4\u5e02\u00b7\u53f0\u7063", "utc": 1513615917000, "level": 0, "avatar": "http://filestoresg1.beetalkmobile.com:8081/file/-8238087549015427326", "name": "\u9b54\u529b\u72fc"}, "content": "\u6843\u5712\u51fa\u7f8e\u5973\ud83d\ude32", "urls": [], "replies": {"first": [], "last": [], "noMoreReplies": true}, "images": [], "id": 77969904}, {"postBy": {"location": "\u65b0\u5317\u5e02\u00b7\u53f0\u7063", "utc": 1513619450000, "level": 0, "avatar": "http://filestoresg1.beetalkmobile.com:8081/file/-5564673405648646899", "name": "\ud83c\udf1f\u83ab\u5fd8\u521d\u8877\ud83c\udf1f"}, "content": "\u597d\u7121\u9ce5\u311b~", "urls": [], "replies": {"first": [], "last": [], "noMoreReplies": true}, "images": [], "id": 77972558}, {"postBy": {"location": "\u9ad8\u96c4\u5e02\u00b7\u53f0\u7063", "utc": 1513767762000, "level": 0, "avatar": "http://filestoresg1.beetalkmobile.com:8081/file/-5114888508513584381", "name": "\u963f\u4efb"}, "content": "\u804a\u7684\u5230\u55ce", "urls": [], "replies": {"first": [], "last": [], "noMoreReplies": true}, "images": [], "id": 78068957}, {"postBy": {"location": "", "utc": 1513842957000, "level": 0, "avatar": "http://filestoresg1.beetalkmobile.com:8081/file/-5114888508513584381", "name": "\u963f\u4efb"}, "content": "\u90a3\u9ebc\u591a\u4eba<br />\u54ea\u8f2a\u5f97\u5230\u6211", "urls": [], "replies": {"first": [], "last": [], "noMoreReplies": true}, "images": [], "id": 78120459}, {"postBy": {"location": "\u53f0\u7063", "utc": 1513966539000, "level": 0, "avatar": "http://filestoresg1.beetalkmobile.com:8081/file/-311956730981762352", "name": "\u5049\u5609"}, "content": "\u55e8\u55e8\u55e8", "urls": [], "replies": {"first": [], "last": [], "noMoreReplies": true}, "images": [], "id": 78215416}, {"postBy": {"location": "\u6843\u5712\u5e02\u00b7\u53f0\u7063", "utc": 1514851066000, "level": 0, "avatar": "http://filestoresg1.beetalkmobile.com:8081/file/-1782685465369683799", "name": "\u6953\u5b88"}, "content": "\u8a66\u8a66\u770b\u4e86\uff5e\uff5e[\u8209\u624b", "urls": [], "replies": {"first": [], "last": [], "noMoreReplies": true}, "images": [], "id": 78842237}, {"postBy": {"location": "\u9ad8\u96c4\u5e02\u00b7\u53f0\u7063", "utc": 1515257034000, "level": 0, "avatar": "http://filestoresg1.beetalkmobile.com:8081/file/-5114888508513584381", "name": "\u963f\u4efb"}, "content": "\u4f86\u804a\u5929\u554a<br />\u9019\u9ebc\u591a\u4eba<br />\u80fd\u804a\u7684\u5230\u55ce", "urls": [], "replies": {"first": [], "last": [], "noMoreReplies": true}, "images": [], "id": 79150882}, {"postBy": {"location": "\u53f0\u7063", "utc": 1515848115000, "level": 0, "avatar": "http://filestoresg1.beetalkmobile.com:8081/file/1265116772019663048", "name": "\u7a4e"}, "content": "\ud83d\ude4b\u200d\u2642\ufe0f\ud83d\ude4b\u200d\u2642\ufe0f\ud83d\ude4b\u200d\u2642\ufe0f", "urls": [], "replies": {"first": [], "last": [], "noMoreReplies": true}, "images": [], "id": 79594698}, {"postBy": {"location": "\u9ad8\u96c4\u5e02\u00b7\u53f0\u7063", "utc": 1516251249000, "level": 0, "avatar": "http://filestoresg1.beetalkmobile.com:8081/file/8831906337875092508", "name": "Mark\ud83d\udc40"}, "content": "\u55e8\u270b", "urls": [], "replies": {"first": [], "last": [], "noMoreReplies": true}, "images": [], "id": 79906483}]}
