{"noMoreComments": true, "cursorEnd": 0, "id": "7677323", "comments": [{"postBy": {"location": "\u53f0\u7063", "utc": 1519283396000, "level": 0, "avatar": "http://filestoresg1.beetalkmobile.com:8081/file/-4124535277499060509", "name": "\u4eca\u65e5\u5f88\u7121\u804a"}, "content": "\u5f88\u50cf", "urls": [], "replies": {"first": [], "last": [], "noMoreReplies": true}, "images": [], "id": 82262727}, {"postBy": {"location": "\u53f0\u7063", "utc": 1520027075000, "level": 0, "avatar": "http://filestoresg1.beetalkmobile.com:8081/file/2410604484971901773", "name": "\u5c11\u4e0a\u871c\u8702IG:JiangSing"}, "content": "\u4f60\u770b\u6211\u871c\u8702\u50cf\u8ecd\u4eba\u55ce?", "urls": [], "replies": {"first": [{"content": "\u600e\u9ebc\u770b\u4e5f\u4e0d\u50cf\ud83d\ude02 \u54ea\u500b\u55ae\u4f4d\u7684", "reply": "", "id": 54028971, "name": "\u900f\u660e\u4eba"}], "last": [{"content": "\u6d77\u8ecd", "reply": "", "id": 54062280, "name": "\u5c11\u4e0a\u871c\u8702IG:JiangSing"}, {"content": "\u6d77\u8ecd\u4e0d\u932f\u8036", "reply": "", "id": 54081545, "name": "\u900f\u660e\u4eba"}], "noMoreReplies": true}, "images": [], "id": 82855933}]}
