{"noMoreComments": true, "cursorEnd": 0, "id": "7420701", "comments": [{"postBy": {"location": "\u53f0\u4e2d\u5e02\u00b7\u53f0\u7063", "utc": 1515592732000, "level": 0, "avatar": "http://filestoresg1.beetalkmobile.com:8081/file/-7264044513645418810", "name": "HatBear"}, "content": "\u6211\u731c\u61c9\u8a72\u5f88\u591a\u4eba\u8ddf\u6211\u4e00\u6a23\u90fd\u60f3\u554f \u5e7e\u6b72\u554a", "urls": [], "replies": {"first": [], "last": [], "noMoreReplies": true}, "images": [], "id": 79409949}, {"postBy": {"location": "\u53f0\u7063", "utc": 1515646823000, "level": 0, "avatar": "http://filestoresg1.beetalkmobile.com:8081/file/5040304247234252626", "name": "\u5929\u5e73\u5ea7"}, "content": "\u8cc7\u6599\u88e1\u6709", "urls": [], "replies": {"first": [{"content": "\u7ffb\u8cc7\u6599\u61f6\u61f6", "reply": "", "id": 52385578, "name": "HatBear"}], "last": [], "noMoreReplies": true}, "images": [], "id": 79445318}]}
