{"noMoreComments": true, "cursorEnd": 0, "id": "7122966", "comments": [{"postBy": {"location": "\u53f0\u7063", "utc": 1511786348000, "level": 0, "avatar": "http://filestoresg1.beetalkmobile.com:8081/file/-7395862744292799834", "name": "\u7121\u76f8\u662f\u7a7a"}, "content": "\u53ef\u4ee5\u770b\u900f\u8863\u670d\u55ce \uff1f\uff01\u5471\u5471", "urls": [], "replies": {"first": [], "last": [], "noMoreReplies": true}, "images": [], "id": 76632840}, {"postBy": {"location": "\u6843\u5712\u5e02\u00b7\u53f0\u7063", "utc": 1511787556000, "level": 0, "avatar": "http://filestoresg1.beetalkmobile.com:8081/file/-7027116243833286412", "name": "\u760b\u72c2\u5c0f\u4fee"}, "content": "\u770b\u982d\u4ec0\u9ebc\u6771\u897f\u554a\u6211\u4e0d\u61c2", "urls": [], "replies": {"first": [{"content": "\u4e00\u5927\u5806\u7169\u4eba\u4e8b", "reply": "", "id": 50962828, "name": "\u5207\u4ed4\u9eb5"}], "last": [], "noMoreReplies": true}, "images": [], "id": 76634017}, {"postBy": {"location": "\u65b0\u5317\u5e02\u00b7\u53f0\u7063", "utc": 1511787794000, "level": 0, "avatar": "http://filestoresg1.beetalkmobile.com:8081/file/6313226443899888652", "name": "\u963f\u967d"}, "content": "\u770b\u900f\u7684\u6771\u897f...\u4e0d\u4e5f\u662f\u9760\u6642\u9593\u8b49\u660e\u51fa\u4f86\u7684\u55ce\ud83e\udd14", "urls": [], "replies": {"first": [], "last": [], "noMoreReplies": true}, "images": [], "id": 76634297}, {"postBy": {"location": "", "utc": 1511793245000, "level": 0, "avatar": "http://filestoresg1.beetalkmobile.com:8081/file/-6522935189956486805", "name": "\u8499\u5176.D.....\u9b6f\u5927\u8178"}, "content": "\u53ea\u770b\u59b3\u7a7f\u5167\u8863\u52a0\u540a\u5e36\u8932\ud83d\ude12<br />", "urls": [], "replies": {"first": [], "last": [], "noMoreReplies": true}, "images": ["http://filestoresg1.beetalkmobile.com:8081/file/469077acd98f5fd6699feedacb78563d"], "id": 76640578}, {"postBy": {"location": "\u53f0\u7063", "utc": 1511803902000, "level": 0, "avatar": "http://filestoresg1.beetalkmobile.com:8081/file/6648592902492097215", "name": "akira"}, "content": "  ", "urls": [], "replies": {"first": [], "last": [], "noMoreReplies": true}, "images": ["http://filestoresg1.beetalkmobile.com:8081/file/d254386dda5d52966a744e638903507b"], "id": 76651220}, {"postBy": {"location": "\u53f0\u5357\u5e02\u00b7\u53f0\u7063", "utc": 1511806113000, "level": 0, "avatar": "http://filestoresg1.beetalkmobile.com:8081/file/-8290755260323952389", "name": "noir"}, "content": "\u8aaa\u7684\u597d\uff01\uff01<br />\u771f\u7684\u6703\u770b\u900f\u770b\u7834\u5f88\u591a\u4e8b\u60c5", "urls": [], "replies": {"first": [], "last": [], "noMoreReplies": true}, "images": [], "id": 76652517}, {"postBy": {"location": "\u9ad8\u96c4\u5e02\u00b7\u53f0\u7063", "utc": 1511828165000, "level": 0, "avatar": "http://filestoresg1.beetalkmobile.com:8081/file/-2235156493621955838", "name": "\u5c0f\u5c0f\u6bdb\u7684\u7238\u7238"}, "content": "\u60a3\u96e3\u66f4\u53ef\u4ee5\u5427\uff01\u6240\u8b02\u60a3\u96e3\u898b\u771f\u60c5\u3002", "urls": [], "replies": {"first": [], "last": [], "noMoreReplies": true}, "images": [], "id": 76660696}, {"postBy": {"location": "Tainan City\u00b7Taiwan", "utc": 1511842030000, "level": 0, "avatar": "http://filestoresg1.beetalkmobile.com:8081/file/-4336732237680403117", "name": "\u5149  \u7fdf"}, "content": "\u70ba\u4ec0\u9ebc\u6211\u7684\u6642\u9593\u53ea\u8b93\u6211\u53d8\u8001\u3002", "urls": [], "replies": {"first": [], "last": [], "noMoreReplies": true}, "images": [], "id": 76670499}, {"postBy": {"location": "\u53f0\u7063", "utc": 1511848668000, "level": 0, "avatar": "http://filestoresg1.beetalkmobile.com:8081/file/1", "name": "\u6709\u7de3\u4eba"}, "content": "\u4f60\u7a7f\u9019\u6a23 \uff0c\u6211\u90fd\u770b\u4e0d\u900f \uff01\uff01", "urls": [], "replies": {"first": [], "last": [], "noMoreReplies": true}, "images": [], "id": 76676264}, {"postBy": {"location": "\u65b0\u5317\u5e02\u00b7\u53f0\u7063", "utc": 1511853090000, "level": 0, "avatar": "http://filestoresg1.beetalkmobile.com:8081/file/-6275649513642379775", "name": "walker \u9f9c\u871c"}, "content": "\u6d3b\u8d8a\u4e45\u770b\u8d8a\u591a\uff0c\u770b\u8457\u770b\u8457\u5c31\u7fd2\u6163\uff0c\u898b\u602a\u4e0d\u602a", "urls": [], "replies": {"first": [], "last": [], "noMoreReplies": true}, "images": ["http://filestoresg1.beetalkmobile.com:8081/file/5e6265dd1cf7b1792982bc0bc2ef08d3"], "id": 76679355}]}
