{"noMoreComments": true, "cursorEnd": 0, "id": "7898212", "comments": [{"postBy": {"location": "\u6843\u5712\u5e02\u00b7\u53f0\u7063", "utc": 1520637473000, "level": 0, "avatar": "http://filestoresg1.beetalkmobile.com:8081/file/-7003841785547627546", "name": "\u6760\u4e0a\u65e5\u4e00"}, "content": "\u6b47\u4e00\u4e0b\u7121\u59a8\u5427\uff01", "urls": [], "replies": {"first": [{"content": "\u6709\u4eba\u544a\u8a34\u6211\uff0c\u81ea\u8ca0\u81ea\u6eff\u5427\uff01\u8b8a\u6210\u50b2\u6162\u3001\u50b2\u6162\u5427!\u6b47\u4e00\u4e0b\u7121\u59a8\u7684\uff0c\u9019\u4e0d\u662f\u602f\u5112\uff0c\u7e7c\u7e8c\u5411\u524d\u9032\u5427\uff01\u6211\u7684\u773c\u6674\u542b\u8457\u773c\u6dda\u3002", "reply": "", "id": 54269765, "name": "peter"}], "last": [{"content": "\u54c8\u54c8\uff0c\u55ef\uff01\u5df2\u7d93\u5230\u4e86\u4e00\u4f11\u606f\u5c31\u6253\u54c8\u6b20\u7684\u5e74\u7eaa\u4e86\u3002", "reply": "\u6760\u4e0a\u65e5\u4e00", "id": 54270546, "name": "peter"}, {"content": "\ud83d\ude01", "reply": "peter", "id": 54270578, "name": "\u6760\u4e0a\u65e5\u4e00"}], "noMoreReplies": false}, "images": [], "id": 83342461}]}
