{"noMoreComments": true, "cursorEnd": 0, "id": "7378737", "comments": [{"postBy": {"location": "\u6843\u5712\u5e02\u00b7\u53f0\u7063", "utc": 1514939974000, "level": 0, "avatar": "http://filestoresg1.beetalkmobile.com:8081/file/8732466488481007942", "name": "\ud83d\udc3e\u6c6a\u6c6a\ud83d\udc36\ud83d\udc3e"}, "content": "\u5176\u5be6\u5f88\u591a\u9109\u6c11<br /><br />\u53ea\u662f\u4f86\u770b\u6e9d\u7684<br /><br />\u6587\u7ae0\u5167\u5bb9\u7121\u8996", "urls": [], "replies": {"first": [], "last": [], "noMoreReplies": true}, "images": [], "id": 78906513}, {"postBy": {"location": "\u53f0\u7063", "utc": 1514944311000, "level": 0, "avatar": "http://filestoresg1.beetalkmobile.com:8081/file/-6331148458496907767", "name": "\u5c0f\u660e"}, "content": "\u77e5\u8db3\u5c31\u662f\u4e00\u500b\u5e78\u798f", "urls": [], "replies": {"first": [], "last": [], "noMoreReplies": true}, "images": [], "id": 78909102}]}
