{"noMoreComments": true, "cursorEnd": 0, "id": "7625415", "comments": [{"postBy": {"location": "", "utc": 1517658987000, "level": 0, "avatar": "http://filestoresg1.beetalkmobile.com:8081/file/1804783490074471178", "name": "\u5b8c\u7f8e\u611b\u60c5.\u70ba\u611b\u8f49\u8eab\u3002"}, "content": "\u54c8\u56c9", "urls": [], "replies": {"first": [], "last": [], "noMoreReplies": true}, "images": [], "id": 81011983}, {"postBy": {"location": "\u6843\u5712\u5e02\u00b7\u53f0\u7063", "utc": 1517820837000, "level": 0, "avatar": "http://filestoresg1.beetalkmobile.com:8081/file/2727362798211880180", "name": "\u9055\u7981\u7528\u6236"}, "content": "\u5348\u5b89", "urls": [], "replies": {"first": [], "last": [], "noMoreReplies": true}, "images": [], "id": 81133777}, {"postBy": {"location": "", "utc": 1517884803000, "level": 0, "avatar": "http://filestoresg1.beetalkmobile.com:8081/file/-1004563289107219710", "name": "Melo"}, "content": "\u59d0\u59d0\u6709\u9152 \u6211\u6709\u6545\u4e8b", "urls": [], "replies": {"first": [], "last": [], "noMoreReplies": true}, "images": [], "id": 81182630}, {"postBy": {"location": "\u53f0\u5357\u5e02\u00b7\u53f0\u7063", "utc": 1517891049000, "level": 0, "avatar": "http://filestoresg1.beetalkmobile.com:8081/file/6735110154431890944", "name": "\u5049\u4efb"}, "content": "\u611b\u5531\u6b4c \uff08\u270c\ufe0f", "urls": [], "replies": {"first": [], "last": [], "noMoreReplies": true}, "images": [], "id": 81187591}, {"postBy": {"location": "\u9ad8\u96c4\u5e02\u00b7\u53f0\u7063", "utc": 1517912001000, "level": 0, "avatar": "http://filestoresg1.beetalkmobile.com:8081/file/7808180732923683676", "name": "\u5fd7\u660e"}, "content": "\u80fd\u804a\u5929\u55ce", "urls": [], "replies": {"first": [], "last": [], "noMoreReplies": true}, "images": [], "id": 81204699}, {"postBy": {"location": "\u53f0\u7063", "utc": 1518088161000, "level": 0, "avatar": "http://filestoresg1.beetalkmobile.com:8081/file/-2910971303889552705", "name": "\u9f8d\u5c11"}, "content": "\u4f60\u4e5f\u559c\u6b22\u559d\u9152\u5417\uff1f", "urls": [], "replies": {"first": [], "last": [], "noMoreReplies": true}, "images": [], "id": 81338580}, {"postBy": {"location": "\u65b0\u5317\u5e02\u00b7\u53f0\u7063", "utc": 1518095286000, "level": 0, "avatar": "http://filestoresg1.beetalkmobile.com:8081/file/7742185862516162560", "name": "\u2764\ufe0fNeko.Cheng"}, "content": "\u5f1f\u5f1f\u90fd\u597d\u6709\u6d3b\u529b\u554a\uff01", "urls": [], "replies": {"first": [], "last": [], "noMoreReplies": true}, "images": [], "id": 81345157}]}
