{"noMoreComments": false, "cursorEnd": 22, "id": "7447057", "comments": [{"postBy": {"location": "\u53f0\u7063", "utc": 1515694283000, "level": 0, "avatar": "http://filestoresg1.beetalkmobile.com:8081/file/-7363993406915282706", "name": "\u5433\u8766"}, "content": "\u8ecd\u5b98\u56c9(\u0e51\u2022\u0300\u1107\u2022\u0301)\u0648 \u2727 ", "urls": [], "replies": {"first": [{"content": "\u600e\u9ebc\u8aaa\u5462", "reply": "", "id": 52390197, "name": "\u59ae\u59ae"}], "last": [{"content": "\u8ab0\u8aaa\u8ecd\u5b98\u597d \u8ecd\u5b98\u6f02\u6d6e\u4e0d\u5b9a \u55ae\u4f4d\u98c4\u4f86\u98c4\u53bb \u58eb\u5b98\u591a\u7a69 \u5c31\u662f\u5f85\u5728\u540c\u4e00\u500b\u55ae\u4f4d ", "reply": "", "id": 56467863, "name": "\u53ed\u5566\u53ed\u53ed\u53ed"}, {"content": "\u8981\u662f\u59b3\u6709\u9060\u5927\u7684\u7406\u60f3 \u5f81\u670d\u4e16\u754c \u8003\u8ecd\u5b98\u5427\n\u8981\u662f\u59b3\u60f3\u4e00\u6280\u4e4b\u9577 \u7a69\u7a69\u5730 \u5c31\u58eb\u5b98\u5427", "reply": "", "id": 56467924, "name": "\u53ed\u5566\u53ed\u53ed\u53ed"}], "noMoreReplies": false}, "images": [], "id": 79487887}, {"postBy": {"location": "", "utc": 1515721813000, "level": 0, "avatar": "http://filestoresg1.beetalkmobile.com:8081/file/1139633930701733376", "name": "\u7070\u8272"}, "content": "\u770b\u4f60\u7684\u76ee\u6a19\u5427<br />\u5982\u679c\u662f\u60f3\u5347\u9ad8\u4f4d<br />\u90a3\u5c31\u8ecd\u5b98<br />\u56e0\u70ba\u4e00\u958b\u59cb\u5c31\u8ecd\u5b98\u624d\u6bd4\u8f03\u5bb9\u6613\u5347\u5230\u6821\u968e\u4ee5\u4e0a<br />\u4f60\u5728\u5b78\u6821\u4e5f\u6703\u8a8d\u8b58\u5f88\u591a\u672a\u4f86\u4e00\u8d77\u5411\u4e0a\u885d\u523a\u7684\u540c\u5b78\u670b\u53cb<br />\u4e0b\u90e8\u968a\u5f8c\u4e92\u76f8\u5e6b\u5fd9\u4e92\u76f8cover<br /><br />\u5982\u679c\u76ee\u6a19\u662f\u7d42\u8eab\u4ff8\u7684\u8a71<br />\u5efa\u8b70\u53ef\u4ee5\u5148\u58eb\u5b98 \u5f8c\u8f49\u8ecd\u5b98<br />\u56e0\u70ba\u8f49\u8ecd\u5b98\u5f8c\u5e74\u8cc7\u7167\u7b97<br />\u800c\u4e14\u5927\u6982\u7576\u5230\u8001\u4e2d\u5c09\u6216\u83dc\u4e0a\u5c09<br />\u5927\u6982\u5e74\u9650\u5c31\u5230\u4e86<br />\u800c\u4e14\u8ecd\u5b98\u7684\u9000\u4f0d\u7d42\u8eab\u4ff8\u597d\u50cf\u6bd4\u8f03\u9ad8\u4e00\u9ede<br />\u53ea\u662f\u73fe\u5728\u7d42\u8eab\u4ff8\u7684\u5236\u5ea6\u4e00\u76f4\u6539\u4f86\u6539\u53bb<br />\u8981\u8003\u616e\u597d<br /><br />\u5982\u679c\u76ee\u6a19\u53ea\u662f\u6c42\u4e00\u4efd\u7a69\u5b9a\u7684\u5de5\u4f5c<br />\u90a3\u5efa\u8b70\u5c31\u4e00\u8def\u58eb\u5b98<br />\u9806\u9806\u7684\u5347\u5230\u58eb\u5b98\u9577<br />\u4f60\u7684\u5de5\u4f5c\u6703\u7121\u6575\u7a69\u5b9a<br />\u800c\u4e14\u80a9\u8180\u4e0a\u7684\u8cac\u4efb\u4e0d\u50cf\u8ecd\u5b98\u90a3\u6a23<br />\u52d5\u4e0d\u52d5\u5c31\u53ef\u80fd\u7533\u8aa1\u8a18\u904e\u5565\u7684<br /><br />\u4ee5\u4e0a\u500b\u4eba\u770b\u6cd5<br />\u7d66\u4f60\u53c3\u8003\u770b\u770b", "urls": [], "replies": {"first": [{"content": "\u76f8\u95dc\u554f\u984c\u53ef\u4ee5\u4f86\u804aXD \u76e1\u91cf\u5e6b\u4f60\u89e3\u7b54", "reply": "", "id": 52394247, "name": "\u7070\u8272"}], "last": [{"content": "\u7a7a\u8ecd\u91cd\u9ede\u662f\u9ad4\u6aa2\u8981\u5148\u904e \u7136\u5f8c\u8ecd\u5b98\u7684\u8a71 \u807d\u8aaa\u7a7a\u8ecd\u5b98\u6821\u4e00\u5e74\u7d1a\u662f\u5b78\u9577\u5b78\u5f1f\u5236\u6700\u91cd\u7684\u5b98\u6821XD \u4f60\u8003\u616e\u8003\u8003\u616e", "reply": "", "id": 52401868, "name": "\u7070\u8272"}, {"content": "\u597d\u7684\u597d\u7684\u8b1d\u8b1d\u4f60", "reply": "\u7070\u8272", "id": 52533988, "name": "\u59ae\u59ae"}], "noMoreReplies": false}, "images": [], "id": 79500088}, {"postBy": {"location": "", "utc": 1515722014000, "level": 0, "avatar": "http://filestoresg1.beetalkmobile.com:8081/file/-1588900940330422528", "name": "\u516b\u723a\u9054"}, "content": "\u58eb\u5b98\u5427 \u770b\u672a\u4f86\u6253\u7b97", "urls": [], "replies": {"first": [{"content": "\u597d\u54c7\u597d\u54c7\u8b1d\u8b1d\u4f60\u56c9", "reply": "", "id": 52395856, "name": "\u59ae\u59ae"}], "last": [], "noMoreReplies": true}, "images": [], "id": 79500213}, {"postBy": {"location": "", "utc": 1515724193000, "level": 0, "avatar": "http://filestoresg1.beetalkmobile.com:8081/file/5629002578249675015", "name": "\ud83d\udc37\u7684\u9ad4\u91cd\ud83d\udc3b\u7684\u8eab\u6750"}, "content": "\u53ef\u4ee5\u5148\u5f9e\u58eb\u5b98\u7576\u8d77\u89ba\u5f97\u8ecd\u5b98\u4e0d\u932f\u7684\u8a71\uff0c\u53ef\u4ee5\u5229\u7528\u58eb\u5b98\u7684\u4e0b\u73ed\u6642\u9593\u6216\u5047\u65e5\u6642\u9593\u53bb\u9032\u4fee\u628a\u5927\u5b78\u8b80\u5b8c\u7136\u5f8c\u518d\u8f49\u8ecd\u5b98\uff0c\u56e0\u70ba\u6211\u4e5f\u662f\u5f9e\u5175\u7576\u8d77\u73fe\u5728\u662f\u58eb\u5b98\u672a\u4f86\u53ef\u4ee5\u6642\u9593\u5230\u4e5f\u8a31\u6703\u8f49\u8ecd\uff5e", "urls": [], "replies": {"first": [{"content": "\u9019\u4e5f\u662f\u53ef\u4ee5\u8003\u616e", "reply": "", "id": 52395868, "name": "\u59ae\u59ae"}], "last": [{"content": "\u8ecd\u4eba\u4e0d\u60f3\u7576\u58eb\u5175\u505a\u5b8c\u56db\u5e74\u53ef\u4ee5\u4e0d\u8981\u505a\u6216\u81e8\u6642\u4e0d\u60f3\u505a\u6709\u9000\u5834\u6a5f\u5236\uff0c\u4f46\u53ea\u6709\u58eb\u5175\u6709", "reply": "\u59ae\u59ae", "id": 52400366, "name": "\ud83d\udc37\u7684\u9ad4\u91cd\ud83d\udc3b\u7684\u8eab\u6750"}, {"content": "\u597d\u7684\u6211\u6703\u8003\u616e\u770b\u770b", "reply": "", "id": 52534007, "name": "\u59ae\u59ae"}], "noMoreReplies": true}, "images": [], "id": 79501704}, {"postBy": {"location": "\u65b0\u5317\u5e02\u00b7\u53f0\u7063", "utc": 1515724881000, "level": 0, "avatar": "http://filestoresg1.beetalkmobile.com:8081/file/8220094088413341704", "name": "Deng jia wei"}, "content": "\u554f\u554f", "urls": [], "replies": {"first": [{"content": "\u807d\u8aaa\u7a7a\u8ecd\u5f88\u96e3\u8003\u662f\u771f\u7684\u55ce", "reply": "", "id": 52395887, "name": "\u59ae\u59ae"}], "last": [{"content": "\u6709\u4fe1\u5fc3\u4ec0\u9ebc\u90fd\u4e0d\u96e3\u5594\uff01", "reply": "", "id": 52399769, "name": "Deng jia wei"}, {"content": "\u9019\u771f\u7684\u5f88\u91cd\u8981", "reply": "Deng jia wei", "id": 52534021, "name": "\u59ae\u59ae"}], "noMoreReplies": true}, "images": [], "id": 79502189}, {"postBy": {"location": "\u9ad8\u96c4\u5e02\u00b7\u53f0\u7063", "utc": 1515743350000, "level": 0, "avatar": "http://filestoresg1.beetalkmobile.com:8081/file/6266446623124411061", "name": "\u8aa0\u610f\u4f86\u4ea4\u670b\u53cb"}, "content": "\u8003\u8ecd\u5b98\u4e0d\u6703\u88ab\u6b3a\u8ca0", "urls": [], "replies": {"first": [{"content": "\u5f8c\u53f0\u5920\u786c\u5427...", "reply": "", "id": 52418458, "name": "Jie Cheng"}], "last": [{"content": "\u8ecd\u5b98\u4e0d\u6703\u88ab\u6b3a\u8ca0\u662f\u54ea\u88e1\u7684\u8aaa\u6cd5\u22ef\u22ef\u6b3a\u8ca0\u4e0d\u6b3a\u8ca0\u4e0d\u662f\u5b98\u968e\u7684\u554f\u984c \u662f\u4eba\u5fc3 \u5728\u90e8\u968a\u6df7\u7684\u5f88\u6158\u5f88\u6158\u7684\u8ecd\u5b98\u6211\u4e5f\u770b\u904e\u4e0d\u5c11 \u800c\u4e14\u8ecd\u5b98\u6c92\u6709\u6b63\u5e38\u7684\u9000\u5834\u6a5f\u5236 \u88ab\u6574\u4e86\u88ab\u5f04\u4e86 \u53ea\u8981\u6536\u5047\u9084\u662f\u5f97\u56de\u71df\u5340\u7e7c\u7e8c\u9762\u5c0d\u9019\u4e00\u5207 \u6c92\u6709\u5f8c\u8def \u8ecd\u5b98\u96d6\u7136\u5728\u5175\u773c\u88e1\u770b\u8d77\u4f86\u6709\u5f88\u591a\u7279\u6b0a \u4f46\u662f\u76f8\u5c0d\u61c9\u7684\u8cac\u4efb\u4e5f\u91cd\u5f88\u591a \u771f\u5fc3\u89ba\u5f97\u7576\u8ecd\u5b98\u771f\u7684\u8981\u8003\u616e\u6e05\u695a", "reply": "", "id": 52592695, "name": "\u7070\u8272"}, {"content": "\u53bb\u8b80\u8ecd\u5b98\u5b78\u6821\u5c31\u77e5\u9053\u4ec0\u9ebc\u662f\u4e0d\u6703\u88ab\u6b3a\u8ca0\u4e86\n\u6240\u8b02\u7684\u5236\u5ea6", "reply": "", "id": 56467986, "name": "\u53ed\u5566\u53ed\u53ed\u53ed"}], "noMoreReplies": false}, "images": [], "id": 79515909}, {"postBy": {"location": "\u53f0\u5357\u5e02\u00b7\u53f0\u7063", "utc": 1515751676000, "level": 0, "avatar": "http://filestoresg1.beetalkmobile.com:8081/file/3906210774272717061", "name": "\u9b5a\u5c3e"}, "content": "\u5982\u679c\u6bd4\u8f03\u80fd\u6297\u58d3\u7684\u5c31\u9078\u8ecd\u5b98", "urls": [], "replies": {"first": [{"content": "\u597d\u54c7\u6211\u77e5\u9053", "reply": "", "id": 52534033, "name": "\u59ae\u59ae"}], "last": [], "noMoreReplies": true}, "images": [], "id": 79522994}, {"postBy": {"location": "\u53f0\u7063", "utc": 1515753726000, "level": 0, "avatar": "http://filestoresg1.beetalkmobile.com:8081/file/3164833170711950538", "name": "\u871c\u6c41\u96de\u817f"}, "content": "\u8ecd\u5b98\u5427\uff01 \u4e0d\u6703\u656c\u79ae\u4e5f\u53ef\u4ee5\u73a9\u58eb\u5175", "urls": [], "replies": {"first": [{"content": "\u54c8\u54c8\u5225\u9019\u6a23\u54c8\u54c8\u597d\u597d\u76f8\u8655\u963f", "reply": "", "id": 52534054, "name": "\u59ae\u59ae"}, {"content": "\u8ecd\u4e2d\u9ed1\u6697\uff0c\u73fe\u5728\u8981\u56de\u53bb\u53d7\u96e3\u4e86", "reply": "", "id": 52559970, "name": "\u871c\u6c41\u96de\u817f"}], "last": [], "noMoreReplies": true}, "images": [], "id": 79524540}, {"postBy": {"location": "\u53f0\u4e2d\u5e02\u00b7\u53f0\u7063", "utc": 1515753895000, "level": 0, "avatar": "http://filestoresg1.beetalkmobile.com:8081/file/-5558810816001829500", "name": "\u7965\u7965"}, "content": "\u7576\u5175\u6700\u597d", "urls": [], "replies": {"first": [{"content": "\u771f\u7684\u55ce", "reply": "", "id": 52534057, "name": "\u59ae\u59ae"}, {"content": "\u7576\u7136\u5566 \u5148\u4e86\u89e3\u9069\u61c9 \u7136\u5f8c\u6709\u5927\u5b78\u5b78\u6b77\u53ef\u4ee5\u8f49\u8ecd\u5b98 \u60f3\u9577\u671f\u7559\u5728\u9023\u4e0a\u53ef\u4ee5\u8f49\u58eb\u5b98 \u5fc3\u60c5\u4e0d\u597d\u56db\u5e74\u9000\u4f0d ", "reply": "", "id": 52535342, "name": "\u7965\u7965"}], "last": [], "noMoreReplies": true}, "images": [], "id": 79524675}, {"postBy": {"location": "", "utc": 1515768010000, "level": 0, "avatar": "http://filestoresg1.beetalkmobile.com:8081/file/5954865923564747783", "name": "\u5929\u5922"}, "content": "\u8ecd\u5b98\u58d3\u529b\u5927 \u4e0d\u53ea\u8981\u5c0d\u4e0a\u9084\u8981\u5c0d\u4e0b \u9577\u9060\u4f86\u8aaa\u798f\u5229\u6bd4\u8f03\u597d<br />\u58eb\u5b98\u76f8\u5c0d\u7684\u58d3\u529b\u6c92\u6709\u90a3\u9ebc\u5927 \u505a\u597d\u672c\u52d9\u5de5\u4f5c\u5c31\u5f88\u5c11\u53d7\u5230\u8cac\u96e3 \u798f\u5229\u5c31\u6c92\u6709\u8ecd\u5b98\u4f86\u7684\u597d<br />\u8003\u616e\u6e05\u695a\u518d\u6c7a\u5b9a\u8981\u9078\u54ea\u689d\u8def\u5427", "urls": [], "replies": {"first": [{"content": "\u597d\u6211\u77e5\u9053\u56c9\u8b1d\u8b1d\u4f60", "reply": "", "id": 52534062, "name": "\u59ae\u59ae"}], "last": [], "noMoreReplies": true}, "images": [], "id": 79538903}, {"postBy": {"location": "\u53f0\u6e7e\u7701\u00b7\u4e2d\u56fd", "utc": 1515768304000, "level": 0, "avatar": "http://filestoresg1.beetalkmobile.com:8081/file/8574409506432377246", "name": "\u715e\u6c23a\u6d6a"}, "content": "\u8ecd\u5b98\u58d3\u529b\u5927\uff0c\u4f46\u9322\u591a<br />\u58eb\u5b98\u5de5\u4f5c\u591a\uff0c\u4e8b\u591a\uff0c\u9322\u6c92\u8ecd\u5b98\u591a", "urls": [], "replies": {"first": [{"content": "\u6211\u6703\u597d\u597d\u60f3\u60f3\u770b\u7684", "reply": "", "id": 52534068, "name": "\u59ae\u59ae"}], "last": [], "noMoreReplies": true}, "images": [], "id": 79539252}, {"postBy": {"location": "\u5f70\u5316\u7e23\u00b7\u53f0\u7063", "utc": 1515773602000, "level": 0, "avatar": "http://filestoresg1.beetalkmobile.com:8081/file/-6000699054159341553", "name": "\u7159\u6d88\u96f2\u6563\uff5e\u32a3\u6d41\u6c13\u8ce4\u5154\u32a3"}, "content": "\u5404\u6709\u5343\u79cb", "urls": [], "replies": {"first": [{"content": "\u597d\u7684\u597d\u7684", "reply": "", "id": 52534074, "name": "\u59ae\u59ae"}, {"content": "\u55ef\u54fc\u22ef", "reply": "\u59ae\u59ae", "id": 52538675, "name": "\u7159\u6d88\u96f2\u6563\uff5e\u32a3\u6d41\u6c13\u8ce4\u5154\u32a3"}], "last": [], "noMoreReplies": true}, "images": [], "id": 79545035}, {"postBy": {"location": "", "utc": 1515864717000, "level": 0, "avatar": "http://filestoresg1.beetalkmobile.com:8081/file/6762327481738675712", "name": "Hans"}, "content": "\u8981\u7576\u8ecd\u5b98\u6700\u597d\u662f\u8ecd\u6821\u6b63\u671f\u751f\uff0c\u5347\u9077\u6a5f\u6703\u6bd4\u8f03\u5927\uff0c\u8a8d\u8b58\u5e7e\u500b\u5c08\u696d\u8ecd\u5b98\u73ed\u7684\u5f8c\u4f86\u90fd\u5347\u4e0d\u4e0a\u53bb\u5c31\u9000\u4f0d\u4e86\uff0c\u5c09\u7d1a\u6700\u591a17\u5e74\uff0c\u6c92\u5347\u4e0a\u53bb\u5c31\u8981\u9000\u4f0d\u4e86", "urls": [], "replies": {"first": [{"content": "\u539f\u4f86\u963f\u597d\u7684", "reply": "", "id": 52534098, "name": "\u59ae\u59ae"}], "last": [], "noMoreReplies": true}, "images": [], "id": 79613273}, {"postBy": {"location": "\u53f0\u4e2d\u5e02\u00b7\u53f0\u7063", "utc": 1515868995000, "level": 0, "avatar": "http://filestoresg1.beetalkmobile.com:8081/file/1645250786930362840", "name": "\u868a\u5b50"}, "content": "\u58eb\u5b98\u85aa\u6c34\u6bd4\u8f03\u4f4e\uff0c\u4f46\u4e0d\u5bb9\u6613\u8abf\u55ae\u4f4d\uff0c\u8ecd\u5b98\u85aa\u6c34\u9ad8\uff0c\u4f46\u56e0\u6b77\u7df4\u5404\u7a2e\u8ecd\u8077\u800c\u9700\u8abf\u55ae\u4f4d\u6216\u5916\u5cf6\uff0c\u5169\u500b\u65b9\u5411\u7684\u58d3\u529b\u90fd\u4e0d\u5c11\uff0c\u5c31\u770b\u59b3\u7684\u5b98\u904b\u5982\u4f55\u4e86", "urls": [], "replies": {"first": [{"content": "\u597d\u6211\u77e5\u9053\u8b1d\u8b1d\u4f60", "reply": "", "id": 52534106, "name": "\u59ae\u59ae"}], "last": [], "noMoreReplies": true}, "images": [], "id": 79616503}, {"postBy": {"location": "\u53f0\u5357\u5e02\u00b7\u53f0\u7063", "utc": 1515871974000, "level": 0, "avatar": "http://filestoresg1.beetalkmobile.com:8081/file/1210670055505405899", "name": "three sec glue"}, "content": "\u58eb\u5b98\u8ecd\u5b98\u57fa\u672c\u4e0a\u90fd\u662f\u5e79\u90e8\u7d1a\uff0c\u6709\u9818\u5c0e\u80fd\u529b\u6700\u91cd\u8981", "urls": [], "replies": {"first": [{"content": "\u597d\u6211\u77e5\u9053", "reply": "", "id": 52534119, "name": "\u59ae\u59ae"}], "last": [], "noMoreReplies": true}, "images": [], "id": 79618279}, {"postBy": {"location": "\u6843\u5712\u5e02\u00b7\u53f0\u7063", "utc": 1515898308000, "level": 0, "avatar": "http://filestoresg1.beetalkmobile.com:8081/file/-113395910102665355", "name": "\u8001\u738b"}, "content": "\u7576\u7136\u8ecd\u5b98\uff0c\u9000\u4f11\u5949\u5dee\u5f88\u591a", "urls": [], "replies": {"first": [{"content": "\u597d\u7684", "reply": "", "id": 52534127, "name": "\u59ae\u59ae"}], "last": [], "noMoreReplies": true}, "images": [], "id": 79631649}, {"postBy": {"location": "\u65b0\u5317\u5e02\u00b7\u53f0\u7063", "utc": 1515909817000, "level": 0, "avatar": "http://filestoresg1.beetalkmobile.com:8081/file/-4130892724003503807", "name": "\u6df1\u7d2b\u8272"}, "content": "\u55e8\u00a0 \u4eca\u5929\u7684\u4f60\u904e\u7684\u597d\u55ce\u00a0\u00a0 \u958b\u5fc3\u55ce?", "urls": [], "replies": {"first": [{"content": "\u958b\u5fc3\u54e6\ud83d\ude02\ud83d\ude02\ud83d\ude02", "reply": "", "id": 52534129, "name": "\u59ae\u59ae"}, {"content": "\u55ef\uff01\n\u7e7c\u7e8c\u4fdd\u6301\u4e0b\u53bb\u5537\n\u65e9\u665a\u6eab\u5dee\u5927\u00a0\u00a0 \n\u4e5f\u8981\u8a18\u5f97\u591a\u7a7f\u4fdd\u6696\u7684\u8863\u670d\u624d\u4e0d\u6703\u611f\u5192\u5537", "reply": "", "id": 52552535, "name": "\u6df1\u7d2b\u8272"}], "last": [], "noMoreReplies": true}, "images": [], "id": 79641425}, {"postBy": {"location": "\u53f0\u7063", "utc": 1515918302000, "level": 0, "avatar": "http://filestoresg1.beetalkmobile.com:8081/file/-2463476673781137807", "name": "\ud83d\udc22\u6301\u7e8c\u55ae\u8eab\u4e2d\ud83c\udf35"}, "content": "\u58eb\u5b98<br />\u4e0d\u904e\u6700\u597d\u6709\u5927\u5b78\u5b78\u6b77<br /><br />\u8ecd\u5b98\u6703\u56db\u8655\u8f2a\u8abf \u800c\u4e14\u6709\u5347\u9077\u58d3\u529b<br />(\u4e00\u5b9a\u6642\u9593\u5167\u6c92\u5347\u4e0a\u53bb\u5f37\u5236\u6dd8\u6c70)<br />\u58eb\u5b98\u53ea\u8981\u4e0b\u58eb\u4ee5\u4e0a\u5c31\u5b89\u5168\u591a\u4e86\u3002<br /><br />\u9664\u975e\u4f60\u5f88\u6703\u52fe\u5fc3\u9b25\u89d2\u641e\u5df4\u7d50\uff0c\u5426\u5247\u4e0d\u63a8\u8ecd\u5b98\u3002\u800c\u4e14\u4f60\u9084\u8981\u71d2\u9999\u62dc\u4f5b\u5e0c\u671b\u4e0b\u5c64\u5225\u51fa\u5305\u3002", "urls": [], "replies": {"first": [{"content": "\u597d\u7684\u54c8\u54c8\u8b1d\u8b1d\u4f60", "reply": "", "id": 52534137, "name": "\u59ae\u59ae"}], "last": [], "noMoreReplies": true}, "images": [], "id": 79649021}, {"postBy": {"location": "\u9ad8\u96c4\u5e02\u00b7\u53f0\u7063", "utc": 1515992678000, "level": 0, "avatar": "http://filestoresg1.beetalkmobile.com:8081/file/-7858279962093394678", "name": "\u5927\u4ec1\u54e5"}, "content": "\u8ecd\u5b98\u6bd4\u58eb\u5b98\u85aa\u6c34\u591a\u4e00\u500d\uff0c\u8ecd\u5b98 \u4e00\u958b\u59cb43000\u591a \u58eb\u5b98\u4e00\u958b\u59cb 36000\u591a \uff0c\u8ecd\u5b98\u7ba1\u696d\u52d9\u6216\u7ba1\u58eb\u5b98\u9577\u4ee5\u4e0b\uff0c\u58eb\u5b98\u7ba1\u696d\u52d9\u6216\u7ba1\u5175\u4ee5\u4e0b\uff0c\u770b\u59b3\u8868\u73fe\u5982\u4f55\u4e0d\u7136\u5c31\u88ab\u76ef", "urls": [], "replies": {"first": [{"content": "\u5176\u5be6\u8981\u5b78\u505a\u4eba", "reply": "", "id": 52534147, "name": "\u59ae\u59ae"}], "last": [{"content": "\u90a3\u4f60\u77e5\u9053\u6211\u5011\u4e00\u5175\u5c31\u6703\u7576\u773e\u6d17\u81c9\u8ecd\u5b98\u55ce\uff1f\n\u6c92\u7576\u5230\u4e0a\u5c09\u524d\u5e7e\u4e4e\u90fd\u662f\u75db\u82e6\u7684\n\u4e0d\u8981\u53ea\u7528\u968e\u7d1a\u4f86\u8861\u91cf\u9a19\u4eba\n\u4e0d\u6562\u8aaa\u73fe\u5be6\u5594", "reply": "", "id": 55152548, "name": "\u5b89\u6293\u8fb2"}, {"content": "\u6211\u53ea\u662f\u500b\u4e0a\u5175 \u9000\u4e00\u5e74\u4e86 \u505a\u904e\u56db\u5e74\u3002\u8ecd\u5b98 \u5c11\u6821 \u526f\u5ea7 \u8f14\u5c0e\u9577 \u53ea\u6703\u5439\u51b7\u6c23 \u804a\u804a\u5929 \u9019\u6a23\u5c31\u80fd\u8cfa\u4e00\u500b\u6708\u7684\u516d\u842c\u591a \u9760\u4e00\u5f35\u5634\u4e5f\u4e0d\u505a\u4e8b \u53ea\u6703\u7576\u7c73\u87f2 \u5ee2\u7269\u4e00\u500b \u6211\u5011\u4e8c\u5175\u4e00\u5175\u770b\u5230\u4e5f\u633a\u89ba\u5f97 \u60b2\u54c0 \u53ef\u6190\u53c8\u5f88\u6c23 \u53ea\u6703\u627e\u9ebb\u7169 \u9084\u4e0d\u505a\u4e8b \u9760\u4e00\u5f35\u5634\u6253\u5929\u4e0b", "reply": "", "id": 55239414, "name": "\u5927\u4ec1\u54e5"}], "noMoreReplies": false}, "images": [], "id": 79706722}]}
