{"noMoreComments": true, "cursorEnd": 0, "id": "7190413", "comments": [{"postBy": {"location": "\u9ad8\u96c4\u5e02\u00b7\u53f0\u7063", "utc": 1515338360000, "level": 0, "avatar": "http://filestoresg1.beetalkmobile.com:8081/file/5527935453247411742", "name": "Wen__hsu"}, "content": "\u611f\u4eba", "urls": [], "replies": {"first": [], "last": [], "noMoreReplies": true}, "images": [], "id": 79217722}, {"postBy": {"location": "", "utc": 1515865779000, "level": 0, "avatar": "http://filestoresg1.beetalkmobile.com:8081/file/-5855427178105093965", "name": "\u5875\u7af9"}, "content": "\u9019\u90e8\u4e0d\u932f\u770b\uff0c\u63a8\u3002", "urls": [], "replies": {"first": [], "last": [], "noMoreReplies": true}, "images": [], "id": 79614139}]}
