{"noMoreComments": true, "cursorEnd": 0, "id": "7158442", "comments": [{"postBy": {"location": "\u6843\u5712\u5e02\u00b7\u53f0\u7063", "utc": 1512229496000, "level": 0, "avatar": "http://filestoresg1.beetalkmobile.com:8081/file/5943183614516575275", "name": "\u7d05\u7334"}, "content": "\u52a0\u6cb9\uff0c\u9858\u59b3\u65e9\u65e5\u8d70\u51fa\u4f86", "urls": [], "replies": {"first": [{"content": "\u4e0d\u662f\u6211\u5566\ud83d\ude2c", "reply": "", "id": 51128939, "name": "Hsiao ling"}], "last": [{"content": "\u54c8\u54c8\uff01\u4e00\u958b\u59cb\u5c31\u6b6a\u6a13\u5bb3\u6211\u5927\u7b11\ud83d\ude02\ud83d\ude02\ud83d\ude02", "reply": "Hsiao ling", "id": 51132671, "name": "\u541b\u7fa8"}, {"content": "\u6211\u50cf\u6028\u5a66\u55ce\ud83d\ude25", "reply": "\u541b\u7fa8", "id": 51137427, "name": "Hsiao ling"}], "noMoreReplies": true}, "images": [], "id": 76956538}, {"postBy": {"location": "\u65b0\u5317\u5e02\u00b7\u53f0\u7063", "utc": 1512233447000, "level": 0, "avatar": "http://filestoresg1.beetalkmobile.com:8081/file/2525134013877545519", "name": "14"}, "content": "\u5c11\u53bb\u4ecb\u5165\u5225\u4eba\u7684\u611f\u60c5\u554f\u984c\u5427\uff01<br /><br />\u505a\u5f97\u597d\u6c92\u734e\u8cde<br /><br />\u6709\u4e8b\u60c5\u7b97\u4f60\u7684", "urls": [], "replies": {"first": [{"content": "\u7576\u7136\u2026\u2026\u6211\u53c8\u6c92\u6709\u6536\u8aee\u8a62\u8cbb\ud83d\ude0e", "reply": "", "id": 51131073, "name": "Hsiao ling"}], "last": [], "noMoreReplies": true}, "images": [], "id": 76960813}, {"postBy": {"location": "\u65b0\u5317\u5e02\u00b7\u53f0\u7063", "utc": 1512239695000, "level": 0, "avatar": "http://filestoresg1.beetalkmobile.com:8081/file/-6371542318339128524", "name": "\u541b\u7fa8"}, "content": "\u6c42\u8a8d\u8b58\uff01\ud83d\ude1c\uff08\u6211\u662f\u4f86\u4e82\u7684\u2026\u2026\ud83d\ude05\ud83d\ude05\ud83d\ude05<br />\u770b\u4f86\u4f60\u6d17\u8166\u529f\u529b\u9084\u4e0d\u5920\u5537\uff01\u9019\u88e1\u6709\u4e00\u672c\u79d8\u7b08\uff0c\u770b\u4f60\u8ddf\u6211\u6709\u7de3\u9019\u672c\u5c31\u7b97\u4f6010\u584a\u9322\uff0c\u4ee5\u5f8c\u7dad\u8b77\u4e16\u754c\u548c\u5e73\u9019\u500b\u4efb\u52d9\u5c31\u4ea4\u7d66\u4f60\u4e86\uff01", "urls": [], "replies": {"first": [{"content": "\u6211\u4e0d\u8981\u2026\u2026\u53c8\u4e0d\u662f\u5403\u98fd\u6490\u8457", "reply": "", "id": 51137432, "name": "Hsiao ling"}], "last": [], "noMoreReplies": true}, "images": ["http://filestoresg1.beetalkmobile.com:8081/file/09632c7eca212d5ff8dfd3df71f49326"], "id": 76965585}, {"postBy": {"location": "\u53f0\u7063", "utc": 1512256346000, "level": 0, "avatar": "http://filestoresg1.beetalkmobile.com:8081/file/-7685663220343387252", "name": "\u8d85\u7d1a\u8fb2\u592b"}, "content": "\u53ef\u80fd\u9001\u5979\u5341\u4e09\u500b\u5b57\uff0c\u5c0d\u4e0d\u8d77\uff0c\u8acb\u539f\u8ad2\u6211\uff0c\u8b1d\u8b1d\u4f60\uff0c\u6211\u611b\u4f60\u3002", "urls": [], "replies": {"first": [{"content": "\u5df2\u7d93\u9001\u5979\u5343\u5343\u842c\u842c\u7684\u5b57\uff0c\u611b\u5230\u5361\u6158\u6b7b\u5566\u2026\u2026\u6c92\u7528", "reply": "", "id": 51137444, "name": "Hsiao ling"}], "last": [{"content": "\u90a3\u5c31\u770b\u5979\u7684\u9020\u5316\u4e86", "reply": "", "id": 51138159, "name": "\u8d85\u7d1a\u8fb2\u592b"}, {"content": "\u963f\u5f4c\u9640\u4f5b\u2026\u2026\u6211\u5df2\u76e1\u529b", "reply": "\u8d85\u7d1a\u8fb2\u592b", "id": 51139583, "name": "Hsiao ling"}], "noMoreReplies": true}, "images": [], "id": 76972302}, {"postBy": {"location": "\u9ad8\u96c4\u5e02\u00b7\u53f0\u7063", "utc": 1512266506000, "level": 0, "avatar": "http://filestoresg1.beetalkmobile.com:8081/file/-5318043050793257643", "name": "\u661f\u8fb0\u8776\u96e8"}, "content": "\u8aaa\u7684\u771f\u597d \uff0c\u53ea\u8981\u59b3\u904e\u5f97\u6bd4\u4ed6\u597d  \u6bd4\u4ed6\u5feb\u6a02   \u4ed6\u6703\u5f8c\u6094\u7684 \u2026", "urls": [], "replies": {"first": [{"content": "\u5176\u5be6\u9019\u6cd5\u5247\u7537\u5973\u901a\u7528\ud83d\ude02", "reply": "", "id": 51139472, "name": "Hsiao ling"}], "last": [], "noMoreReplies": true}, "images": [], "id": 76977584}]}
