{"noMoreComments": false, "cursorEnd": 20, "id": "7128138", "comments": [{"postBy": {"location": "\u53f0\u7063", "utc": 1511850433000, "level": 0, "avatar": "http://filestoresg1.beetalkmobile.com:8081/file/-1534163961553931051", "name": "\u541b\u83ab\u7b11"}, "content": "\ud83d\ude4a", "urls": [], "replies": {"first": [], "last": [], "noMoreReplies": true}, "images": [], "id": 76677589}, {"postBy": {"location": "Kaohsiung City\u00b7Taiwan", "utc": 1511853020000, "level": 0, "avatar": "http://filestoresg1.beetalkmobile.com:8081/file/8447175102625649203", "name": "\u5d50\u591c"}, "content": "\u6211\u9084\u662f\u6bd4\u8f03\u559c\u6b61\u5403\u8089\ud83d\ude02\ud83d\ude02", "urls": [], "replies": {"first": [], "last": [], "noMoreReplies": true}, "images": [], "id": 76679318}, {"postBy": {"location": "\u53f0\u5357\u5e02\u00b7\u53f0\u7063", "utc": 1511853116000, "level": 0, "avatar": "http://filestoresg1.beetalkmobile.com:8081/file/7723324816672669625", "name": "\u9b41"}, "content": "\u5929\u59295\u852c\u679c\uff0c\u5065\u5eb7999", "urls": [], "replies": {"first": [], "last": [], "noMoreReplies": true}, "images": [], "id": 76679378}, {"postBy": {"location": "\u53f0\u4e2d\u5e02\u00b7\u53f0\u7063", "utc": 1511853496000, "level": 0, "avatar": "http://filestoresg1.beetalkmobile.com:8081/file/-4978326965834116796", "name": "\u937e\u5176\u5906"}, "content": "\u6211\u8ddf\u59b3\u6c92\u4ec0\u9ebc\u597d\u8ac7\u7684^^\u9664\u4e86\u8ac7\u6200\u611b\uff5e", "urls": [], "replies": {"first": [], "last": [], "noMoreReplies": true}, "images": [], "id": 76679677}, {"postBy": {"location": "\u53f0\u5357\u5e02\u00b7\u53f0\u7063", "utc": 1511853802000, "level": 0, "avatar": "http://filestoresg1.beetalkmobile.com:8081/file/4986961432599669765", "name": "\u9673\u7d05\u8336"}, "content": "\u55e8 \u53f0\u5357\u4efb\u59b3\u597d", "urls": [], "replies": {"first": [], "last": [], "noMoreReplies": true}, "images": [], "id": 76679901}, {"postBy": {"location": "\u53f0\u5357\u5e02\u00b7\u53f0\u7063", "utc": 1511853886000, "level": 0, "avatar": "http://filestoresg1.beetalkmobile.com:8081/file/1047958826945553682", "name": "\u55ae\u624b\u89e3"}, "content": "\u4f60\u7684\u8077\u696d\u662f\u4e0d\u662f\u5c0f\u5077\u554a\uff1f\uff1f\uff1f<br /><br /><br /><br /><br /><br /><br /><br />\u56e0\u70ba\u4f60\u5077\u8d70\u6211\u7684\u5fc3\u4e86\ud83d\ude02\ud83d\ude02\ud83d\ude02\ud83d\ude02", "urls": [], "replies": {"first": [], "last": [], "noMoreReplies": true}, "images": [], "id": 76679955}, {"postBy": {"location": "\u9ad8\u96c4\u5e02\u00b7\u53f0\u7063", "utc": 1511857274000, "level": 0, "avatar": "http://filestoresg1.beetalkmobile.com:8081/file/-402527901455495775", "name": "You Liang"}, "content": "\u55e8\u55e8", "urls": [], "replies": {"first": [], "last": [], "noMoreReplies": true}, "images": [], "id": 76682392}, {"postBy": {"location": "\u53f0\u7063", "utc": 1511867282000, "level": 0, "avatar": "http://filestoresg1.beetalkmobile.com:8081/file/-5343051464351779430", "name": "\u868a\u5b50"}, "content": "\u54e6\u5f4c\u9640\u4f5b ", "urls": [], "replies": {"first": [], "last": [], "noMoreReplies": true}, "images": [], "id": 76690095}, {"postBy": {"location": "\u6843\u5712\u5e02\u00b7\u53f0\u7063", "utc": 1511867433000, "level": 0, "avatar": "http://filestoresg1.beetalkmobile.com:8081/file/8944552382338655693", "name": "\u6d2a\u5c0f\u5f18"}, "content": "\u55e8\u53ef\u4ee5\u8a8d\u8b58\u55ce", "urls": [], "replies": {"first": [], "last": [], "noMoreReplies": true}, "images": [], "id": 76690251}, {"postBy": {"location": "\u53f0\u5357\u5e02\u00b7\u53f0\u7063", "utc": 1511868194000, "level": 0, "avatar": "http://filestoresg1.beetalkmobile.com:8081/file/-7508366989892207496", "name": "\u908a\u7de3\u4eba"}, "content": "\u53ef\u611b\u2665", "urls": [], "replies": {"first": [], "last": [], "noMoreReplies": true}, "images": [], "id": 76690890}, {"postBy": {"location": "\u53f0\u4e2d\u5e02\u00b7\u53f0\u7063", "utc": 1511868530000, "level": 0, "avatar": "http://filestoresg1.beetalkmobile.com:8081/file/-1903458034622986932", "name": "\u3002\u7965\u3002"}, "content": "\u5403\u5e7e\u5929\u4e86\uff0c\u54c8\u54c8", "urls": [], "replies": {"first": [], "last": [], "noMoreReplies": true}, "images": [], "id": 76691226}, {"postBy": {"location": "\u65b0\u7af9\u7e23\u00b7\u53f0\u7063", "utc": 1511868729000, "level": 0, "avatar": "http://filestoresg1.beetalkmobile.com:8081/file/-9172022639064933064", "name": "\u80a5\u561f\u561f"}, "content": "\u53ef\u662f\u6211\u662f\u8089\u8036...", "urls": [], "replies": {"first": [], "last": [], "noMoreReplies": true}, "images": [], "id": 76691413}, {"postBy": {"location": "\u6843\u5712\u5e02\u00b7\u53f0\u7063", "utc": 1511871391000, "level": 0, "avatar": "http://filestoresg1.beetalkmobile.com:8081/file/-2053821748937931728", "name": "\u68e0\u68e0"}, "content": "\u539f\u4f86\u59b3\u6c92\u6709\u540d\u5b57<br />\u7576\u7136 \u600e\u9ebc\u6709\u5e78\u76f4\u547c\u4ed9\u5973\u7684\u540d\u8af1\ud83d\ude1c", "urls": [], "replies": {"first": [], "last": [], "noMoreReplies": true}, "images": [], "id": 76693810}, {"postBy": {"location": "\u53f0\u7063", "utc": 1511871732000, "level": 0, "avatar": "http://filestoresg1.beetalkmobile.com:8081/file/770144131740373609", "name": "\u9673\u7761\u7761"}, "content": "\u6700\u8fd1\u6211\u90fd\u5403\u8089\u4e86\uff0c\u54c8\u54c8\u54c8\uff5e\u8981\u8b8a\u80a5\u80a5\u554a", "urls": [], "replies": {"first": [], "last": [], "noMoreReplies": true}, "images": [], "id": 76694188}, {"postBy": {"location": "\u53f0\u4e2d\u5e02\u00b7\u53f0\u7063", "utc": 1511871798000, "level": 0, "avatar": "http://filestoresg1.beetalkmobile.com:8081/file/3390051655198986487", "name": "\u8a00\u8eab\u5bf8"}, "content": "\u9019\u662f\u7b11\u8a71\u55ce\uff1f", "urls": [], "replies": {"first": [], "last": [], "noMoreReplies": true}, "images": [], "id": 76694244}, {"postBy": {"location": "\u65b0\u5317\u5e02\u00b7\u53f0\u7063", "utc": 1511877301000, "level": 0, "avatar": "http://filestoresg1.beetalkmobile.com:8081/file/-734632086594371894", "name": "\u300a\u5fd7\u6c23\u300b"}, "content": "\u9019\u62db\u6709\u4eba\u7528\u904e\u4e86", "urls": [], "replies": {"first": [], "last": [], "noMoreReplies": true}, "images": [], "id": 76700409}, {"postBy": {"location": "Taoyuan City\u00b7Taiwan", "utc": 1511933131000, "level": 0, "avatar": "http://filestoresg1.beetalkmobile.com:8081/file/6632411392262519915", "name": "Shawn"}, "content": "\u73fe\u5728\u59b9\u5b50\u4e5f\u8981\u64a9\u4eba\u5537\u2026", "urls": [], "replies": {"first": [], "last": [], "noMoreReplies": true}, "images": [], "id": 76739251}, {"postBy": {"location": "\u53f0\u5357\u5e02\u00b7\u53f0\u7063", "utc": 1511938519000, "level": 0, "avatar": "http://filestoresg1.beetalkmobile.com:8081/file/1972787766375434805", "name": "\u658c"}, "content": "\u4e2d\u4e86", "urls": [], "replies": {"first": [], "last": [], "noMoreReplies": true}, "images": [], "id": 76743333}, {"postBy": {"location": "\u53f0\u7063", "utc": 1511938667000, "level": 0, "avatar": "http://filestoresg1.beetalkmobile.com:8081/file/4906407918343283464", "name": "\u6708"}, "content": "\u606d\u559c\u59b3\u64a9\u5230\u4eba\u4e86", "urls": [], "replies": {"first": [], "last": [], "noMoreReplies": true}, "images": [], "id": 76743432}]}
