{"noMoreComments": true, "cursorEnd": 0, "id": "7738286", "comments": [{"postBy": {"location": "\u65b0\u5317\u5e02\u00b7\u53f0\u7063", "utc": 1518944198000, "level": 0, "avatar": "http://filestoresg1.beetalkmobile.com:8081/file/-5167278038542415319", "name": "Ig\u624d\u56de:yls10261025"}, "content": "\u8f9b\u82e6\u5566", "urls": [], "replies": {"first": [{"content": "\u771f\u7684hen\u51b7", "reply": "", "id": 53590514, "name": "oooo"}], "last": [], "noMoreReplies": true}, "images": [], "id": 81987480}]}
