{"noMoreComments": true, "cursorEnd": 0, "id": "7604755", "comments": [{"postBy": {"location": "", "utc": 1527344890000, "level": 0, "avatar": "http://filestoresg1.beetalkmobile.com:8081/file/-2758889055782101482", "name": "\u6c99\u767c\u4e0a\u7684\u6ce2\u7279\u591a"}, "content": "\u744b\u5144\u5f1f\u592a\u4e45\u6c92\u5230\u967d\u9593\u4f86\u73a9\u5152\u22ef<br />\u653e\u500b\u990c\uff0c\u540a\u4e00\u4e0b\uff5e<br /><br />\u9019\u54ea\u88e1\u672a\u547d\u540d\uff0c<br />\u4e3b\u984c\u4e0d\u5c31\u662f:\u201d\u552f\u6211\u7368\u5c0a\uff0c\u9806\u751f\u9006\u4ea1\u201d\u54a9", "urls": [], "replies": {"first": [], "last": [], "noMoreReplies": true}, "images": [], "id": 88979987}]}
